ascii_cards/__init__.py
ascii_cards/cards.py
tests/__init__.py
tests/test_cards.py
simple_ascii_cards-0.1.dist-info/LICENSE
simple_ascii_cards-0.1.dist-info/METADATA
simple_ascii_cards-0.1.dist-info/WHEEL
simple_ascii_cards-0.1.dist-info/top_level.txt
simple_ascii_cards-0.1.dist-info/RECORD
