Metadata-Version: 2.1
Name: simple-ascii-cards
Version: 0.1
Summary: A simple ASCII card display package
Home-page: https://github.com/naivoder/ascii_cards
Author: Cameron Redovian
Author-email: naivoder@gmail.com
Project-URL: Source, https://github.com/naivoder/ascii_cards
Keywords: cards games ascii
Classifier: Development Status :: 3 - Alpha
Classifier: Intended Audience :: Developers
Classifier: Topic :: Games/Entertainment
Classifier: License :: OSI Approved :: MIT License
Classifier: Programming Language :: Python :: 3
Classifier: Programming Language :: Python :: 3.7
Classifier: Programming Language :: Python :: 3.8
Classifier: Programming Language :: Python :: 3.9
License-File: LICENSE
